rwkv2onnx_python.cp38-win_amd64.pyd
rwkv2onnx/.gitignore
rwkv2onnx/__init__.py
rwkv2onnx/__main__.py
rwkv2onnx/convert_to_fr.py
rwkv2onnx-0.0.14.dist-info/METADATA
rwkv2onnx-0.0.14.dist-info/WHEEL
rwkv2onnx-0.0.14.dist-info/entry_points.txt
rwkv2onnx-0.0.14.dist-info/top_level.txt
rwkv2onnx-0.0.14.dist-info/RECORD
