Metadata-Version: 2.1
Name: rwkv2onnx
Version: 0.0.14
Summary: RWKV to ONNX (powered by Faster RWKV)
Author-email: daquexian <daquexian566@gmail.com>
Keywords: deep-learning,RWKV
Classifier: Programming Language :: Python :: 3
Requires-Python: >=3.8
Requires-Dist: importlib-resources
Requires-Dist: msgpack
Requires-Dist: rich
